desktop_wallpaper.py
py_wallpaper.py
wallpaper.py
desktop_wallpaper-1.0.1.dist-info/METADATA
desktop_wallpaper-1.0.1.dist-info/WHEEL
desktop_wallpaper-1.0.1.dist-info/top_level.txt
desktop_wallpaper-1.0.1.dist-info/RECORD
